setup.cfg
setup.py
stackit/__init__.py
stackit/stackit_core.py
stackit.egg-info/PKG-INFO
stackit.egg-info/SOURCES.txt
stackit.egg-info/dependency_links.txt
stackit.egg-info/entry_points.txt
stackit.egg-info/requires.txt
stackit.egg-info/top_level.txt