Metadata-Version: 1.1
Name: stackit
Version: 0.1.6
Summary: stackit sends smart StackOverflow queries from your command line
Home-page: http://stackitfor.me
Author: SB Hacks Crew
Author-email: lukas.schwab@gmail.com
License: MIT
Download-URL: https://github.com/lukasschwab/stackit/tarball/0.1.6
Keywords: error stderr stack overflow stackoverflow stack exchange stackexchange
Platform: UNKNOWN
